tests/__init__.py
tests/test_bubble_sort.py
tests/test_insertion_sort.py
tests/test_quick_sort.py
siwp2005_billy_sorting_algorithms-1.0.dist-info/LICENSE
siwp2005_billy_sorting_algorithms-1.0.dist-info/METADATA
siwp2005_billy_sorting_algorithms-1.0.dist-info/WHEEL
siwp2005_billy_sorting_algorithms-1.0.dist-info/top_level.txt
siwp2005_billy_sorting_algorithms-1.0.dist-info/RECORD
